{
  "_meta": {
    "version": "2.1",
    "name": "zkap-design-system",
    "type": "palette",
    "created": "2025-02-03",
    "format": "hsla",
    "_usage": "Alpha 값만 변경하여 opacity 조절 가능. 예: hsla(221, 43%, 11%, 0.5)"
  },

  "grey": {
    "50": "hsla(210, 17%, 98%, 1)",
    "100": "hsla(220, 14%, 96%, 1)",
    "200": "hsla(216, 14%, 91%, 1)",
    "300": "hsla(216, 12%, 84%, 1)",
    "400": "hsla(214, 10%, 64%, 1)",
    "500": "hsla(217, 10%, 46%, 1)",
    "600": "hsla(214, 14%, 34%, 1)",
    "700": "hsla(217, 20%, 26%, 1)",
    "800": "hsla(214, 29%, 16%, 1)",
    "900": "hsla(221, 43%, 11%, 1)"
  },

  "blue": {
    "50": "hsla(235, 100%, 95%, 1)",
    "100": "hsla(234, 100%, 88%, 1)",
    "200": "hsla(231, 100%, 79%, 1)",
    "300": "hsla(229, 100%, 70%, 1)",
    "400": "hsla(228, 100%, 63%, 1)",
    "500": "hsla(221, 100%, 50%, 1)",
    "600": "hsla(224, 100%, 47%, 1)",
    "700": "hsla(226, 100%, 44%, 1)",
    "800": "hsla(228, 100%, 42%, 1)",
    "900": "hsla(234, 100%, 38%, 1)"
  },

  "red": {
    "50": "hsla(354, 91%, 95%, 1)",
    "100": "hsla(352, 87%, 89%, 1)",
    "200": "hsla(356, 71%, 75%, 1)",
    "300": "hsla(0, 70%, 65%, 1)",
    "400": "hsla(358, 79%, 60%, 1)",
    "500": "hsla(3, 89%, 57%, 1)",
    "600": "hsla(1, 73%, 54%, 1)",
    "700": "hsla(0, 68%, 49%, 1)",
    "800": "hsla(359, 69%, 45%, 1)",
    "900": "hsla(0, 74%, 40%, 1)"
  },

  "orange": {
    "50": "hsla(42, 97%, 94%, 1)",
    "100": "hsla(37, 98%, 85%, 1)",
    "200": "hsla(35, 98%, 75%, 1)",
    "300": "hsla(33, 98%, 65%, 1)",
    "400": "hsla(31, 99%, 57%, 1)",
    "500": "hsla(29, 100%, 50%, 1)",
    "600": "hsla(26, 97%, 49%, 1)",
    "700": "hsla(22, 94%, 48%, 1)",
    "800": "hsla(18, 91%, 47%, 1)",
    "900": "hsla(12, 95%, 45%, 1)"
  },

  "yellow": {
    "50": "hsla(55, 93%, 95%, 1)",
    "100": "hsla(53, 97%, 88%, 1)",
    "200": "hsla(52, 98%, 81%, 1)",
    "300": "hsla(51, 98%, 73%, 1)",
    "400": "hsla(50, 99%, 66%, 1)",
    "500": "hsla(49, 99%, 62%, 1)",
    "600": "hsla(46, 99%, 60%, 1)",
    "700": "hsla(43, 99%, 59%, 1)",
    "800": "hsla(40, 99%, 57%, 1)",
    "900": "hsla(33, 99%, 55%, 1)"
  },

  "green": {
    "50": "hsla(143, 60%, 93%, 1)",
    "100": "hsla(147, 58%, 83%, 1)",
    "200": "hsla(148, 56%, 72%, 1)",
    "300": "hsla(150, 54%, 61%, 1)",
    "400": "hsla(151, 56%, 53%, 1)",
    "500": "hsla(151, 66%, 44%, 1)",
    "600": "hsla(152, 68%, 39%, 1)",
    "700": "hsla(153, 71%, 34%, 1)",
    "800": "hsla(153, 74%, 29%, 1)",
    "900": "hsla(155, 80%, 21%, 1)"
  },

  "teal": {
    "50": "hsla(174, 53%, 92%, 1)",
    "100": "hsla(175, 54%, 81%, 1)",
    "200": "hsla(176, 51%, 68%, 1)",
    "300": "hsla(177, 50%, 55%, 1)",
    "400": "hsla(178, 60%, 45%, 1)",
    "500": "hsla(177, 88%, 36%, 1)",
    "600": "hsla(178, 88%, 33%, 1)",
    "700": "hsla(179, 87%, 28%, 1)",
    "800": "hsla(179, 88%, 24%, 1)",
    "900": "hsla(180, 93%, 17%, 1)"
  },

  "purple": {
    "50": "hsla(275, 67%, 95%, 1)",
    "100": "hsla(275, 67%, 87%, 1)",
    "200": "hsla(275, 64%, 79%, 1)",
    "300": "hsla(275, 62%, 70%, 1)",
    "400": "hsla(275, 65%, 63%, 1)",
    "500": "hsla(275, 67%, 56%, 1)",
    "600": "hsla(276, 55%, 53%, 1)",
    "700": "hsla(277, 56%, 48%, 1)",
    "800": "hsla(278, 59%, 43%, 1)",
    "900": "hsla(280, 66%, 35%, 1)"
  },

  "navy": {
    "50": "hsla(199, 46%, 92%, 1)",
    "100": "hsla(201, 48%, 80%, 1)",
    "200": "hsla(202, 48%, 68%, 1)",
    "300": "hsla(204, 45%, 58%, 1)",
    "400": "hsla(205, 50%, 51%, 1)",
    "500": "hsla(206, 58%, 46%, 1)",
    "600": "hsla(208, 60%, 41%, 1)",
    "700": "hsla(210, 67%, 36%, 1)",
    "800": "hsla(211, 70%, 31%, 1)",
    "900": "hsla(214, 77%, 24%, 1)"
  },

  "static": {
    "white": "hsla(0, 0%, 100%, 1)",
    "black": "hsla(0, 0%, 0%, 1)"
  }
}
